parameter_optimizer/__init__.py
parameter_optimizer/config_manager.py
parameter_optimizer/core.py
parameter_optimizer/data_models.py
parameter_optimizer/metric_evaluator.py
parameter_optimizer/result_cache.py
parameter_optimizer/test_runner.py
parameter_optimizer-1.0.0.dist-info/licenses/LICENSE
parameter_optimizer-1.0.0.dist-info/METADATA
parameter_optimizer-1.0.0.dist-info/WHEEL
parameter_optimizer-1.0.0.dist-info/top_level.txt
parameter_optimizer-1.0.0.dist-info/RECORD
