Metadata-Version: 2.4
Name: parameter-optimizer
Version: 1.0.0
Summary: A reusable parameter optimization package for systematic testing of parameter combinations
Home-page: https://github.com/parameter-optimizer/parameter-optimizer
Author: Parameter Optimizer Team
Author-email: Parameter Optimizer Team <contact@parameter-optimizer.dev>
Maintainer-email: Parameter Optimizer Team <contact@parameter-optimizer.dev>
License: MIT License
Project-URL: Homepage, https://github.com/parameter-optimizer/parameter-optimizer
Project-URL: Documentation, https://github.com/parameter-optimizer/parameter-optimizer#readme
Project-URL: Repository, https://github.com/parameter-optimizer/parameter-optimizer
Project-URL: Bug Tracker, https://github.com/parameter-optimizer/parameter-optimizer/issues
Keywords: optimization,parameters,testing,machine-learning,hyperparameters
Classifier: Development Status :: 5 - Production/Stable
Classifier: Intended Audience :: Developers
Classifier: Intended Audience :: Science/Research
Classifier: License :: OSI Approved :: MIT License
Classifier: Operating System :: OS Independent
Classifier: Programming Language :: Python :: 3
Classifier: Programming Language :: Python :: 3.8
Classifier: Programming Language :: Python :: 3.9
Classifier: Programming Language :: Python :: 3.10
Classifier: Programming Language :: Python :: 3.11
Classifier: Programming Language :: Python :: 3.12
Classifier: Topic :: Scientific/Engineering
Classifier: Topic :: Software Development :: Libraries :: Python Modules
Classifier: Topic :: System :: Benchmark
Requires-Python: >=3.8
License-File: LICENSE
Requires-Dist: psutil>=5.8.0
Provides-Extra: dev
Requires-Dist: pytest>=7.0.0; extra == "dev"
Requires-Dist: hypothesis>=6.0.0; extra == "dev"
Requires-Dist: black>=22.0.0; extra == "dev"
Requires-Dist: flake8>=4.0.0; extra == "dev"
Requires-Dist: mypy>=0.950; extra == "dev"
Provides-Extra: test
Requires-Dist: pytest>=7.0.0; extra == "test"
Requires-Dist: hypothesis>=6.0.0; extra == "test"
Requires-Dist: pytest-cov>=3.0.0; extra == "test"
Dynamic: author
Dynamic: home-page
Dynamic: license-file
Dynamic: requires-python
